arl/__init__.py
arl/py.typed
arl/session.py
arl/types.py
arl/warmpool.py
arl/arl_client/__init__.py
arl/arl_client/api_client.py
arl/arl_client/api_response.py
arl/arl_client/configuration.py
arl/arl_client/exceptions.py
arl/arl_client/py.typed
arl/arl_client/rest.py
arl/arl_client/api/__init__.py
arl/arl_client/api/default_api.py
arl/arl_client/models/__init__.py
arl/arl_client/models/condition.py
arl/arl_client/models/list_meta.py
arl/arl_client/models/object_meta.py
arl/arl_client/models/sandbox.py
arl/arl_client/models/sandbox_list.py
arl/arl_client/models/sandbox_spec.py
arl/arl_client/models/sandbox_spec_resources.py
arl/arl_client/models/sandbox_spec_resources_claims_inner.py
arl/arl_client/models/sandbox_spec_resources_limits_value.py
arl/arl_client/models/sandbox_status.py
arl/arl_client/models/task.py
arl/arl_client/models/task_list.py
arl/arl_client/models/task_spec.py
arl/arl_client/models/task_status.py
arl/arl_client/models/task_step.py
arl/arl_client/models/warm_pool.py
arl/arl_client/models/warm_pool_list.py
arl/arl_client/models/warm_pool_spec.py
arl/arl_client/models/warm_pool_spec_template.py
arl/arl_client/models/warm_pool_spec_template_spec.py
arl/arl_client/models/warm_pool_spec_template_spec_affinity.py
arl/arl_client/models/warm_pool_spec_template_spec_affinity_node_affinity.py
arl/arl_client/models/warm_pool_spec_template_spec_affinity_node_affinity_preferred_during_scheduling_ignored_during_execution_inner.py
arl/arl_client/models/warm_pool_spec_template_spec_affinity_node_affinity_preferred_during_scheduling_ignored_during_execution_inner_preference.py
arl/arl_client/models/warm_pool_spec_template_spec_affinity_node_affinity_preferred_during_scheduling_ignored_during_execution_inner_preference_match_expressions_inner.py
arl/arl_client/models/warm_pool_spec_template_spec_affinity_node_affinity_required_during_scheduling_ignored_during_execution.py
arl/arl_client/models/warm_pool_spec_template_spec_affinity_pod_affinity.py
arl_env-0.1.4.dist-info/METADATA
arl_env-0.1.4.dist-info/WHEEL
arl_env-0.1.4.dist-info/RECORD
