Metadata-Version: 2.4
Name: arl-env
Version: 0.1.4
Summary: ARL Infrastructure - Python SDK for Kubernetes-based Agent Runtime Layer
Project-URL: Homepage, https://github.com/Lincyaw/agent-env
Project-URL: Repository, https://github.com/Lincyaw/agent-env
Project-URL: Documentation, https://github.com/Lincyaw/agent-env/tree/main/docs
Project-URL: Issues, https://github.com/Lincyaw/agent-env/issues
Author: ARL Infrastructure Team
License: Apache-2.0
Keywords: agent,kubernetes,operator,runtime,sandbox,task-execution
Classifier: Development Status :: 3 - Alpha
Classifier: Intended Audience :: Developers
Classifier: License :: OSI Approved :: Apache Software License
Classifier: Programming Language :: Python :: 3
Classifier: Programming Language :: Python :: 3.10
Classifier: Programming Language :: Python :: 3.11
Classifier: Programming Language :: Python :: 3.12
Requires-Python: >=3.10
Requires-Dist: kubernetes>=28.0.0
Requires-Dist: pydantic>=2
Requires-Dist: python-dateutil>=2.8.2
Requires-Dist: typing-extensions>=4.7.1
Requires-Dist: urllib3<3.0.0,>=1.25.3
Provides-Extra: dev
Requires-Dist: mypy>=1.13.0; extra == 'dev'
Requires-Dist: pytest-cov>=2.8.1; extra == 'dev'
Requires-Dist: pytest>=7.2.1; extra == 'dev'
Requires-Dist: ruff>=0.8.0; extra == 'dev'
